{
    "title": "Sukkur District",
    "area": {
        "value": 5165,
        "unit_long": "square kilometers",
        "unit_short": "Sq. Kms"
    },
    "population": {
        "year": {
            "1981": 560566,
            "1998": 908373
        },
        "gender": {
            "male": {
                "percentage": 59.83
            },
            "female": {
                "percentage": 31.32
            }
        },
        "ratio": {
            "type": "males per 100 females",
            "value": 113.7
        },
        "density": {
            "value": 175.9,
            "unit_long": "per square kilometers",
            "unit_short": "per Sq. Kms"
        },
        "urban": {
            "percentage": 50.87,
            "value": 462105
        },
        "rural": {
            "percentage": 49.12,
            "value": 446268
        }
    },
    "administration": {
        "union_councils": 46,
        "town_committees": 3,
        "cantonment": 1,
        "mauzas": 251
    },
    "litracy_ratio": {
        "age": "10+",
        "percentage": 46.6
    },
    "growth_rate": {
        "type": "average",
        "percentage": 2.88,
        "year": {
            "from": 1981,
            "to": 1998
        }
    },
    "household": {
        "type": "average",
        "size": 6.6
    },
    "housing": {
        "units": {
            "total": 138553,
            "pacca": {
                "value": 53926,
                "percentage": 38.92
            }
        },
        "have_utilities": {
            "electricity": {
                "value": 101853,
                "percentage": 73.51
            },
            "water": {
                "type": "piped",
                "value": 52190,
                "percentage": 37.67
            },
            "gas": {
                "value": 41230,
                "percentage": 29.76
            }
        }
    },
    "location": {
        "lat": 27.5715029,
        "lng": 69.2447234
    }
}